[{"branchId":"1A68846","loginId":null,"sessionPermissions":[],"dealerCode":"BARX","platformBranchId":"1A75193","dealerBranchId":"BARCLAYS","id":"c4d538c9-7388-554d-9f2c-c19b3cfaaac5","assetClass":"FixedIncome","relationship":"Relationship:Bilateral","account":[]},{"branchId":"1A68846","loginId":null,"sessionPermissions":[],"dealerCode":"BARD","platformBranchId":"1A75193","dealerBranchId":"101710","id":"836b9569-5c69-592c-a1bc-1e4b5ea1bef6","assetClass":"FixedIncome","relationship":"Relationship:Bilateral","account":[]},{"branchId":"1A68846","loginId":null,"sessionPermissions":[],"dealerCode":"BBVA","platformBranchId":"1A75193","dealerBranchId":"100613","id":"5a597476-201d-54e2-b132-e349b806f872","assetClass":"FixedIncome","relationship":"Relationship:Bilateral","account":[]},{"branchId":"1A68846","loginId":null,"sessionPermissions":[],"dealerCode":"LTIN","platformBranchId":"1A75193","dealerBranchId":"100613","id":"be49d9a8-ac8f-5bfb-9931-1a6d4be58901","assetClass":"FixedIncome","relationship":"Relationship:Bilateral","account":[]},{"branchId":"1A68846","loginId":null,"sessionPermissions":[],"dealerCode":"BCAP","platformBranchId":"1A75193","dealerBranchId":"BARCLAYS","id":"d625bf70-58c9-5239-afd8-6bad6a17b900","assetClass":"FixedIncome","relationship":"Relationship:Bilateral","account":[]},{"branchId":"1A68846","loginId":null,"sessionPermissions":[],"dealerCode":"BKCM","platformBranchId":"1A75193","dealerBranchId":"100441","id":"2d3e7f14-a102-5337-8ce9-91aa8d212cb7","assetClass":"FixedIncome","relationship":"Relationship:Bilateral","account":[]},{"branchId":"1A68846","loginId":null,"sessionPermissions":[],"dealerCode":"BMOC","platformBranchId":"1A75193","dealerBranchId":"101661","id":"ab0c37a2-559b-56d1-947b-80f599a96a01","assetClass":"FixedIncome","relationship":"Relationship:Bilateral","account":[]},{"branchId":"1A68846","loginId":null,"sessionPermissions":[],"dealerCode":"PARI","platformBranchId":"1A75193","dealerBranchId":"BNP","id":"46d59ec8-8f76-5219-88c5-7ec0689d147a","assetClass":"FixedIncome","relationship":"Relationship:Bilateral","account":[]},{"branchId":"1A68846","loginId":null,"sessionPermissions":[],"dealerCode":"BNPP","platformBranchId":"1A75193","dealerBranchId":"1A87716","id":"75326fe8-3c77-5b40-ae57-e5956f3846b0","assetClass":"FixedIncome","relationship":"Relationship:Bilateral","account":[]},{"branchId":"1A68846","loginId":null,"sessionPermissions":[],"dealerCode":"BOFA","platformBranchId":"1A75193","dealerBranchId":"1A95676","id":"03895504-e40e-59e5-a60a-a31078429754","assetClass":"FixedIncome","relationship":"Relationship:Bilateral","account":[]},{"branchId":"1A68846","loginId":null,"sessionPermissions":[],"dealerCode":"BCAP","platformBranchId":"1A75193","dealerBranchId":"BARCLAYS","id":"d625bf70-58c9-5239-afd8-6bad6a17b900","assetClass":"FixedIncome","relationship":"Relationship:Bilateral","account":[]},{"branchId":"1A68846","loginId":null,"sessionPermissions":[],"dealerCode":"SANT","platformBranchId":"1A75193","dealerBranchId":"101755","id":"b798ed9b-7d1d-51c0-8810-d7e01a375f54","assetClass":"FixedIncome","relationship":"Relationship:Bilateral","account":[]},{"branchId":"1A68846","loginId":null,"sessionPermissions":[],"dealerCode":"CABR","platformBranchId":"1A75193","dealerBranchId":"1B76084","id":"0bd2c6cf-6602-55e4-b029-a88425244c19","assetClass":"FixedIncome","relationship":"Relationship:Bilateral","account":[]},{"branchId":"1A68846","loginId":null,"sessionPermissions":[],"dealerCode":"CFCO","platformBranchId":"1A75193","dealerBranchId":"100534","id":"ee12dea8-ce85-5f49-ba74-1d74d7006f61","assetClass":"FixedIncome","relationship":"Relationship:Bilateral","account":[]},{"branchId":"1A68846","loginId":null,"sessionPermissions":[],"dealerCode":"CITI","platformBranchId":"1A75193","dealerBranchId":"100546","id":"c7bc7180-a92a-5b0e-b0e0-a47a3ea368a5","assetClass":"FixedIncome","relationship":"Relationship:Bilateral","account":[]},{"branchId":"1A68846","loginId":null,"sessionPermissions":[],"dealerCode":"LYON","platformBranchId":"1A75193","dealerBranchId":"1B81589","id":"440e2fba-b807-5b79-b30d-3d0315b82f2e","assetClass":"FixedIncome","relationship":"Relationship:Bilateral","account":[]},{"branchId":"1A68846","loginId":null,"sessionPermissions":[],"dealerCode":"CALY","platformBranchId":"1A75193","dealerBranchId":"1B81589","id":"e8bc9de0-43f6-548a-838f-8d9591127ae6","assetClass":"FixedIncome","relationship":"Relationship:Bilateral","account":[]},{"branchId":"1A68846","loginId":null,"sessionPermissions":[],"dealerCode":"CS","platformBranchId":"1A75193","dealerBranchId":"CSFB","id":"7a923c48-1cb6-50fb-8c70-15f1fdde61eb","assetClass":"FixedIncome","relationship":"Relationship:Bilateral","account":[]},{"branchId":"1A68846","loginId":null,"sessionPermissions":[],"dealerCode":"FBCO","platformBranchId":"1A75193","dealerBranchId":"CSFB","id":"f56ac5a7-ade1-56a7-8e1f-c826d4c59e71","assetClass":"FixedIncome","relationship":"Relationship:Bilateral","account":[]},{"branchId":"1A68846","loginId":null,"sessionPermissions":[],"dealerCode":"CWMK","platformBranchId":"1A75193","dealerBranchId":"101627","id":"3bdbd743-41e9-50a9-ab93-a82c51a56b57","assetClass":"FixedIncome","relationship":"Relationship:Bilateral","account":[]},{"branchId":"1A68846","loginId":null,"sessionPermissions":[],"dealerCode":"DBKS","platformBranchId":"1A75193","dealerBranchId":"DB","id":"f7dcf33d-21c9-58e7-a735-a6d56478bd50","assetClass":"FixedIncome","relationship":"Relationship:Bilateral","account":[]},{"branchId":"1A68846","loginId":null,"sessionPermissions":[],"dealerCode":"DB","platformBranchId":"1A75193","dealerBranchId":"DB","id":"de27b766-c805-5b62-aac7-00c682c95106","assetClass":"FixedIncome","relationship":"Relationship:Bilateral","account":[]},{"branchId":"1A68846","loginId":null,"sessionPermissions":[],"dealerCode":"DAIW","platformBranchId":"1A75193","dealerBranchId":"DAIWA","id":"4b59d8e5-1022-5aad-bb2e-1a3539193b72","assetClass":"FixedIncome","relationship":"Relationship:Bilateral","account":[]},{"branchId":"1A68846","loginId":null,"sessionPermissions":[],"dealerCode":"FTSC","platformBranchId":"1A75193","dealerBranchId":"102570","id":"48f693ec-2e2f-53e7-9522-98dc7750d98b","assetClass":"FixedIncome","relationship":"Relationship:Bilateral","account":[]},{"branchId":"1A68846","loginId":null,"sessionPermissions":[],"dealerCode":"GSCO","platformBranchId":"1A75193","dealerBranchId":"100061","id":"3302c8f8-f933-5b44-93cb-bbe4d7495ae6","assetClass":"FixedIncome","relationship":"Relationship:Bilateral","account":[]},{"branchId":"1A68846","loginId":null,"sessionPermissions":[],"dealerCode":"CAPM","platformBranchId":"1A75193","dealerBranchId":"102604","id":"1b4395a2-08a7-5b72-ae6c-67c68496483f","assetClass":"FixedIncome","relationship":"Relationship:Bilateral","account":[]},{"branchId":"1A68846","loginId":null,"sessionPermissions":[],"dealerCode":"GSCO","platformBranchId":"1A75193","dealerBranchId":"100061","id":"3302c8f8-f933-5b44-93cb-bbe4d7495ae6","assetClass":"FixedIncome","relationship":"Relationship:Bilateral","account":[]},{"branchId":"1A68846","loginId":null,"sessionPermissions":[],"dealerCode":"GS","platformBranchId":"1A75193","dealerBranchId":"100061","id":"3bc32ea1-fb9c-57e3-bc1f-46e985edce71","assetClass":"FixedIncome","relationship":"Relationship:Bilateral","account":[]},{"branchId":"1A68846","loginId":null,"sessionPermissions":[],"dealerCode":"HSBC","platformBranchId":"1A75193","dealerBranchId":"100792","id":"d24ca543-71f2-58c9-b25f-61921cc5060a","assetClass":"FixedIncome","relationship":"Relationship:Bilateral","account":[]},{"branchId":"1A68846","loginId":null,"sessionPermissions":[],"dealerCode":"MZHO","platformBranchId":"1A75193","dealerBranchId":"MIZUHO","id":"19cccce5-5fbe-5685-bcf4-e78e485307f1","assetClass":"FixedIncome","relationship":"Relationship:Bilateral","account":[]},{"branchId":"1A68846","loginId":null,"sessionPermissions":[],"dealerCode":"JANY","platformBranchId":"1A75193","dealerBranchId":"1A70132","id":"8460fae5-eea8-53fb-bf59-57606f1c7b83","assetClass":"FixedIncome","relationship":"Relationship:Bilateral","account":[]},{"branchId":"1A68846","loginId":null,"sessionPermissions":[],"dealerCode":"JEFF","platformBranchId":"1A75193","dealerBranchId":"100054","id":"b51ec5dd-764b-560e-ba1f-6dc02d3c21ac","assetClass":"FixedIncome","relationship":"Relationship:Bilateral","account":[]},{"branchId":"1A68846","loginId":null,"sessionPermissions":[],"dealerCode":"JPMS","platformBranchId":"1A75193","dealerBranchId":"100194","id":"042c5836-0aab-5088-b11a-66e70ef5a80b","assetClass":"FixedIncome","relationship":"Relationship:Bilateral","account":[]},{"branchId":"1A68846","loginId":null,"sessionPermissions":[],"dealerCode":"JPM","platformBranchId":"1A75193","dealerBranchId":"1B34675","id":"b22abf6d-3519-5339-816f-361efa55648b","assetClass":"FixedIncome","relationship":"Relationship:Bilateral","account":[]},{"branchId":"1A68846","loginId":null,"sessionPermissions":[],"dealerCode":"JSEB","platformBranchId":"1A75193","dealerBranchId":"100605","id":"445f0cfa-bee2-5151-95d3-f7c258d643ff","assetClass":"FixedIncome","relationship":"Relationship:Bilateral","account":[]},{"branchId":"1A68846","loginId":null,"sessionPermissions":[],"dealerCode":"KEYB","platformBranchId":"1A75193","dealerBranchId":"102784","id":"0ba3ea23-f049-58bc-905c-0e7f5a4c401b","assetClass":"FixedIncome","relationship":"Relationship:Bilateral","account":[]},{"branchId":"1A68846","loginId":null,"sessionPermissions":[],"dealerCode":"KING","platformBranchId":"1A75193","dealerBranchId":"101665","id":"6b1743e4-879c-51a6-802d-d1eb7452de83","assetClass":"FixedIncome","relationship":"Relationship:Bilateral","account":[]},{"branchId":"1A68846","loginId":null,"sessionPermissions":[],"dealerCode":"LOOP","platformBranchId":"1A75193","dealerBranchId":"1A32136","id":"2432f1f0-9aeb-5994-9f2b-e864a2db9ce8","assetClass":"FixedIncome","relationship":"Relationship:Bilateral","account":[]},{"branchId":"1A68846","loginId":null,"sessionPermissions":[],"dealerCode":"LYSI","platformBranchId":"1A75193","dealerBranchId":"1A56810","id":"a7a6f6a0-defb-5f41-bc49-6751d9a52185","assetClass":"FixedIncome","relationship":"Relationship:Bilateral","account":[]},{"branchId":"1A68846","loginId":null,"sessionPermissions":[],"dealerCode":"MADV","platformBranchId":"1A75193","dealerBranchId":"1B44075","id":"7a2b976f-fabb-5500-976c-d288cdf6277b","assetClass":"FixedIncome","relationship":"Relationship:Bilateral","account":[]},{"branchId":"1A68846","loginId":null,"sessionPermissions":[],"dealerCode":"BAML","platformBranchId":"1A75193","dealerBranchId":"1A95676","id":"7988a805-1514-5af0-8271-c3aaa2fd39bc","assetClass":"FixedIncome","relationship":"Relationship:Bilateral","account":[]},{"branchId":"1A68846","loginId":null,"sessionPermissions":[],"dealerCode":"MSCO","platformBranchId":"1A75193","dealerBranchId":"MS","id":"7692d652-d136-5688-9cb1-666ae12e4da1","assetClass":"FixedIncome","relationship":"Relationship:Bilateral","account":[]},{"branchId":"1A68846","loginId":null,"sessionPermissions":[],"dealerCode":"FBSB","platformBranchId":"1A75193","dealerBranchId":"1B21339","id":"03002b65-1969-544c-9e74-ff1bfd75c647","assetClass":"FixedIncome","relationship":"Relationship:Bilateral","account":[]},{"branchId":"1A68846","loginId":null,"sessionPermissions":[],"dealerCode":"MUFG","platformBranchId":"1A75193","dealerBranchId":"1A54037","id":"50bc0556-6559-5bc8-a5fe-4ca1f21d2a21","assetClass":"FixedIncome","relationship":"Relationship:Bilateral","account":[]},{"branchId":"1A68846","loginId":null,"sessionPermissions":[],"dealerCode":"MZHO","platformBranchId":"1A75193","dealerBranchId":"MIZUHO","id":"19cccce5-5fbe-5685-bcf4-e78e485307f1","assetClass":"FixedIncome","relationship":"Relationship:Bilateral","account":[]},{"branchId":"1A68846","loginId":null,"sessionPermissions":[],"dealerCode":"SMBC","platformBranchId":"1A75193","dealerBranchId":"102924","id":"7a4350d7-0feb-5081-b2b5-2c683a216bd6","assetClass":"FixedIncome","relationship":"Relationship:Bilateral","account":[]},{"branchId":"1A68846","loginId":null,"sessionPermissions":[],"dealerCode":"SUMI","platformBranchId":"1A75193","dealerBranchId":"102924","id":"712d61fb-0cbe-54e2-b2aa-b1b61b06f93b","assetClass":"FixedIncome","relationship":"Relationship:Bilateral","account":[]},{"branchId":"1A68846","loginId":null,"sessionPermissions":[],"dealerCode":"NMRA","platformBranchId":"1A75193","dealerBranchId":"NOMURA","id":"c0388fdd-eca5-5f8b-836b-99de9516d546","assetClass":"FixedIncome","relationship":"Relationship:Bilateral","account":[]},{"branchId":"1A68846","loginId":null,"sessionPermissions":[],"dealerCode":"NOMX","platformBranchId":"1A75193","dealerBranchId":"NOMURA","id":"8a777bea-b50c-5fa4-bd89-6464dffc608b","assetClass":"FixedIncome","relationship":"Relationship:Bilateral","account":[]},{"branchId":"1A68846","loginId":null,"sessionPermissions":[],"dealerCode":"OHIO","platformBranchId":"1A75193","dealerBranchId":"1B76086","id":"97018b24-b345-59fd-9a18-35242acf0b4f","assetClass":"FixedIncome","relationship":"Relationship:Bilateral","account":[]},{"branchId":"1A68846","loginId":null,"sessionPermissions":[],"dealerCode":"WFS","platformBranchId":"1A75193","dealerBranchId":"1A42867","id":"f592ef7a-818a-512d-89f5-26621313bd89","assetClass":"FixedIncome","relationship":"Relationship:Bilateral","account":[]},{"branchId":"1A68846","loginId":null,"sessionPermissions":[],"dealerCode":"WCHV","platformBranchId":"1A75193","dealerBranchId":"1A42867","id":"a74848f1-01dd-5a80-a2b1-b693b7e4d8bc","assetClass":"FixedIncome","relationship":"Relationship:Bilateral","account":[]},{"branchId":"1A68846","loginId":null,"sessionPermissions":[],"dealerCode":"PPSL","platformBranchId":"1A75193","dealerBranchId":"1A74068","id":"70f26eb1-b745-50c7-9164-d05d1ad5d93d","assetClass":"FixedIncome","relationship":"Relationship:Bilateral","account":[]},{"branchId":"1A68846","loginId":null,"sessionPermissions":[],"dealerCode":"PTLV","platformBranchId":"1A75193","dealerBranchId":"1A87716","id":"84ee8c5e-6246-5b47-9e9f-09c0b1d61206","assetClass":"FixedIncome","relationship":"Relationship:Bilateral","account":[]},{"branchId":"1A68846","loginId":null,"sessionPermissions":[],"dealerCode":"RBCD","platformBranchId":"1A75193","dealerBranchId":"101290","id":"509ccc95-46e1-5f92-965b-3daaa2b6899b","assetClass":"FixedIncome","relationship":"Relationship:Bilateral","account":[]},{"branchId":"1A68846","loginId":null,"sessionPermissions":[],"dealerCode":"NWMT","platformBranchId":"1A75193","dealerBranchId":"102604","id":"b314e419-9278-5d09-871d-abff5d19134f","assetClass":"FixedIncome","relationship":"Relationship:Bilateral","account":[]},{"branchId":"1A68846","loginId":null,"sessionPermissions":[],"dealerCode":"RILY","platformBranchId":"1A75193","dealerBranchId":"1B95795","id":"17c43b45-9a47-5055-a302-7f9664aeb3c1","assetClass":"FixedIncome","relationship":"Relationship:Bilateral","account":[]},{"branchId":"1A68846","loginId":null,"sessionPermissions":[],"dealerCode":"RJFI","platformBranchId":"1A75193","dealerBranchId":"102524","id":"e5c43ee9-244b-5f27-8f78-9922136bc99f","assetClass":"FixedIncome","relationship":"Relationship:Bilateral","account":[]},{"branchId":"1A68846","loginId":null,"sessionPermissions":[],"dealerCode":"RBCD","platformBranchId":"1A75193","dealerBranchId":"101290","id":"509ccc95-46e1-5f92-965b-3daaa2b6899b","assetClass":"FixedIncome","relationship":"Relationship:Bilateral","account":[]},{"branchId":"1A68846","loginId":null,"sessionPermissions":[],"dealerCode":"SG","platformBranchId":"1A75193","dealerBranchId":"100166","id":"f1c13012-ad67-595f-a1e8-35fcb2a04805","assetClass":"FixedIncome","relationship":"Relationship:Bilateral","account":[]},{"branchId":"1A68846","loginId":null,"sessionPermissions":[],"dealerCode":"SPGS","platformBranchId":"1A75193","dealerBranchId":"1B95692","id":"1519209a-4f82-5b88-a3af-d29bdb673217","assetClass":"FixedIncome","relationship":"Relationship:Bilateral","account":[]},{"branchId":"1A68846","loginId":null,"sessionPermissions":[],"dealerCode":"STCM","platformBranchId":"1A75193","dealerBranchId":"101691","id":"cdf0f706-b384-5e18-ba6a-c075fe54711e","assetClass":"FixedIncome","relationship":"Relationship:Bilateral","account":[]},{"branchId":"1A68846","loginId":null,"sessionPermissions":[],"dealerCode":"STFL","platformBranchId":"1A75193","dealerBranchId":"102372","id":"784a6829-53ec-5941-b183-6ac1659b1f36","assetClass":"FixedIncome","relationship":"Relationship:Bilateral","account":[]},{"branchId":"1A68846","loginId":null,"sessionPermissions":[],"dealerCode":"SUFI","platformBranchId":"1A75193","dealerBranchId":"100916","id":"1f800933-9165-549d-b71f-afb6617f6d9a","assetClass":"FixedIncome","relationship":"Relationship:Bilateral","account":[]},{"branchId":"1A68846","loginId":null,"sessionPermissions":[],"dealerCode":"SUMI","platformBranchId":"1A75193","dealerBranchId":"102924","id":"712d61fb-0cbe-54e2-b2aa-b1b61b06f93b","assetClass":"FixedIncome","relationship":"Relationship:Bilateral","account":[]},{"branchId":"1A68846","loginId":null,"sessionPermissions":[],"dealerCode":"SWST","platformBranchId":"1A75193","dealerBranchId":"1A76341","id":"d9601c95-adc0-5256-b144-aef7ac795a82","assetClass":"FixedIncome","relationship":"Relationship:Bilateral","account":[]},{"branchId":"1A68846","loginId":null,"sessionPermissions":[],"dealerCode":"TD","platformBranchId":"1A75193","dealerBranchId":"101697","id":"cd13a676-d3d1-58ac-a21e-d57db0a0932c","assetClass":"FixedIncome","relationship":"Relationship:Bilateral","account":[]},{"branchId":"1A68846","loginId":null,"sessionPermissions":[],"dealerCode":"TDSI","platformBranchId":"1A75193","dealerBranchId":"101697","id":"b7dc4723-8ee9-598c-8616-29d00bcdec44","assetClass":"FixedIncome","relationship":"Relationship:Bilateral","account":[]},{"branchId":"1A68846","loginId":null,"sessionPermissions":[],"dealerCode":"TRYN","platformBranchId":"1A75193","dealerBranchId":"1A97423","id":"81ad6733-f0aa-5407-bae1-421e23573021","assetClass":"FixedIncome","relationship":"Relationship:Bilateral","account":[]},{"branchId":"1A68846","loginId":null,"sessionPermissions":[],"dealerCode":"UBSW","platformBranchId":"1A75193","dealerBranchId":"UBS","id":"e3b4f8fb-0d1a-5b85-98fa-6947106173bb","assetClass":"FixedIncome","relationship":"Relationship:Bilateral","account":[]},{"branchId":"1A68846","loginId":null,"sessionPermissions":[],"dealerCode":"WLMS","platformBranchId":"1A75193","dealerBranchId":"1B06986","id":"352ac006-428a-5d25-bb87-a1d8ce1c1f8b","assetClass":"FixedIncome","relationship":"Relationship:Bilateral","account":[]},{"branchId":"1A68846","loginId":null,"sessionPermissions":[],"dealerCode":"MKTX","platformBranchId":"1A75193","dealerBranchId":"1A75193","id":"e0f40828-550a-5cc8-81b3-35b84ac338e8","assetClass":"FixedIncome","relationship":"Relationship:Bilateral","account":[]},{"branchId":"1A68846","loginId":null,"sessionPermissions":[],"dealerCode":"ML","platformBranchId":"1A75193","dealerBranchId":"1A75193","id":"cfeffb17-930d-5ff0-8f5b-3df8f1140714","assetClass":"FixedIncome","relationship":"Relationship:MatchedPrincipal","account":[]}]